{
  "$schema": "https://vega.github.io/schema/vega-lite/v5.json",
  
  "title": {
    "text": "Safemoon Twitter Sentiment",
    "subtitle": "Data scraped from Twitter using Tweepy on 10/11/21",
    "subtitleFontStyle":"italic",
    "subtitleFontSize":10,
    "subtitleColor":"#db1779"
  },
  "height": 250,
  "width": "container",
  "data": {"url": "https://raw.githubusercontent.com/jamiebbb/jamiebbb.github.io/main/data/Safemoon_sentiment_10.11.csv"},
  "mark": "bar",
  "encoding": {
    "x": {"field": "Sentiment", "sort": "descending"},
    "y": {"aggregate": "count", "title": "Number of Tweets"}
  }
}
